{"0":{"DateStamp":"2025-04-08","TimeStamp":"16:38:00","R":{"Scale":"0","Text":"none","MinorProb":null,"MajorProb":null},"S":{"Scale":"0","Text":"none","Prob":null},"G":{"Scale":"0","Text":"none"}},"1":{"DateStamp":"2025-04-08","TimeStamp":"16:38:00","R":{"Scale":null,"Text":null,"MinorProb":"55","MajorProb":"10"},"S":{"Scale":null,"Text":null,"Prob":"5"},"G":{"Scale":"1","Text":"minor"}},"2":{"DateStamp":"2025-04-09","TimeStamp":"00:00:00","R":{"Scale":null,"Text":null,"MinorProb":"55","MajorProb":"10"},"S":{"Scale":null,"Text":null,"Prob":"5"},"G":{"Scale":"0","Text":"none"}},"3":{"DateStamp":"2025-04-10","TimeStamp":"00:00:00","R":{"Scale":null,"Text":null,"MinorProb":"55","MajorProb":"10"},"S":{"Scale":null,"Text":null,"Prob":"5"},"G":{"Scale":"0","Text":"none"}},"-1":{"DateStamp":"2025-04-07","TimeStamp":"16:38:00","R":{"Scale":"0","Text":"none","MinorProb":null,"MajorProb":null},"S":{"Scale":"0","Text":"none","Prob":null},"G":{"Scale":"1","Text":"minor"}}}